utils/__init__.py
utils/http_client.py
utils/transport.py
utils/umicp_client.py
utils/validation.py
vectorizer_sdk-1.3.0.dist-info/licenses/LICENSE
vectorizer_sdk-1.3.0.dist-info/METADATA
vectorizer_sdk-1.3.0.dist-info/WHEEL
vectorizer_sdk-1.3.0.dist-info/entry_points.txt
vectorizer_sdk-1.3.0.dist-info/top_level.txt
vectorizer_sdk-1.3.0.dist-info/RECORD
